<dashboard theme="dark" version="1.1">
  <label>DfE FOUNDATIONAL SERVICES : METRICS DASHBOARD</label>
  <description>Service Security Posture Hardening Programme : v1.01</description>

  <init>
  <!-- ###    <set token="rollup_panel_width">30%</set>
    <set token="data_panel_width">13%</set>
    <set token="data_panel_height">200</set>##### -->
    <set token="c_red">"0xFF0000"</set>
    <set token="c_green">"0x00FF00"</set>
    <set token="c_orange">"0xd94e17"</set>
    <set token="c_blue">"0x0000FF"</set>
  </init>

  

  <fieldset submitButton="false">

    <input type="radio" token="tkn_view_summary">
      <label>View</label>
      <choice value="S">Rolled-Up Summary</choice>
      <choice value="D">Details By Control</choice>
      <default>S</default>
      <change>
        <condition value="S">
          <set token="tkn_view_summary_panels">Y</set>
          <unset token="tkn_view_details_panels"></unset>
        </condition>
        <condition value="D">
          <set token="tkn_view_details_panels">Y</set>
          <unset token="tkn_view_summary_panels"></unset>
        </condition>
      </change>
    </input>

    <input type="checkbox" token="tkn_only_red" searchWhenChanged="true" depends="$tkn_view_details_panels$">
      <label>Show</label>
      <choice value="Y">Only Red</choice>
      <initialValue></initialValue>
      <change>
        <condition value="Y">
          <set token="tkn_view_only_red">Y</set>
        </condition>
        <condition>
          <set token="tkn_view_only_red">N</set>
        </condition>
      </change>
    </input>
  </fieldset>


  
  
  <!-- ################################################# DEFINE HEADER PANEL STYLES FOR ALL ROWS #################################################### -->
  
  <row depends="$nevershow$">
    <panel>
      <html>
        <style>
          .header_r1{
             height: auto; 
             margin: 0px auto 0px auto;
             font-size: 1.1em;
             font-family: Arial, Helvetica, sans-serif;
             color: #AAAAAA; 
          }
          .header_r2{
             height: auto; 
             margin: 0px auto 0px auto;
             font-size: 0.8em;
             font-family: Arial, Helvetica, sans-serif;
             color: #777777; 
             display: block;
          }
          .dashboard-cell.dashboard-layout-panel.last-visible div:empty {
             background: #171d21;
          }
        </style>
      </html>
    </panel>
  </row>
  

    
    
<!-- ###****************** Auto calculate panel widths and height **********************### -->
  <row depends="$never_show$">
    <panel>
      <table>
        <search>
          <query>
index="ssphp_metrics" ssphp.use_case.id="*"
    [| search index="ssphp_metrics"
     | stats max(SSPHP_RUN) as SSPHP_RUN by ssphp.use_case.id
     | eval search_text="(\"ssphp.use_case.id\"=\"".'ssphp.use_case.id'."\" AND SSPHP_RUN=\"".SSPHP_RUN."\")"
     | stats values(search_text) as search_text
     | eval search_text="(".mvjoin(search_text," OR ").")"
    | return $search_text]
| stats count by ssphp.use_case.id
| rex field=ssphp.use_case.id "^(?&lt;uc_type&gt;[^_]*)_(?&lt;uc_no&gt;\d{3})$"
| stats max(uc_no) as max_no_panels, dc(uc_type) as no_rows
| eval no_rows=no_rows+1 ``` for dev only ```
| eval filler_panel_width=1, panel_width=(100-filler_panel_width)/(max_no_panels+2), header_panel_width=panel_width*2, total_width=header_panel_width+filler_panel_width+(panel_width*max_no_panels), panel_width=panel_width."%", header_panel_width=header_panel_width."%", filler_panel_width=filler_panel_width."%", row_height=450/no_rows
          </query>
          <done>
            <set token="rollup_panel_width">$result.header_panel_width$</set>
            <set token="data_panel_width">$result.panel_width$</set>
            <set token="filler_panel_width">$result.filler_panel_width$</set>
            <set token="data_panel_height">$result.row_height$</set>
          </done>
          <earliest>0</earliest>
          <sampleRatio>1</sampleRatio>
        </search>
      </table>
    </panel>
  </row>
